<?xml version="1.0"?>
<!DOCTYPE tsung SYSTEM "/usr/local/share/tsung/tsung-1.0.dtd" []>
<tsung loglevel="notice">
  <clients>
    <client host="localhost" use_controller_vm="true" maxusers="10000" />
  </clients>
  <servers>
    <server host="rails-to-riches.eba-viwn7vp8.us-west-2.elasticbeanstalk.com" port="80" type="tcp" />
  </servers>
  <load>
    <arrivalphase phase="1" duration="60" unit="second">
      <users arrivalrate="4" unit="second"></users>
    </arrivalphase>
    <arrivalphase phase="2" duration="60" unit="second">
      <users arrivalrate="8" unit="second"></users>
    </arrivalphase>
    <arrivalphase phase="3" duration="60" unit="second">
      <users arrivalrate="16" unit="second"></users>
    </arrivalphase>
    <arrivalphase phase="4" duration="60" unit="second">
      <users arrivalrate="32" unit="second"></users>
    </arrivalphase>
    <arrivalphase phase="5" duration="60" unit="second">
      <users arrivalrate="64" unit="second"></users>
    </arrivalphase>
    <arrivalphase phase="6" duration="60" unit="second">
      <users arrivalrate="128" unit="second"></users>
    </arrivalphase>
    <arrivalphase phase="7" duration="60" unit="second">
      <users arrivalrate="256" unit="second"></users>
    </arrivalphase>
  </load>
  <sessions>
    <session name="browse_restaurants" probability="100" type="ts_http">      
        <transaction name="reviews_and_comments">
          <!-- View Reviews and comments for the Restaurant -->
          <request subst="true">
            <http url="/api/restaurants/1/reviews_paged?page=1&amp;per_page=100" method="GET">
            </http>
          </request>
        </transaction>
    </session>
  </sessions>
</tsung>
